mcp_bc_server/__init__.py
mcp_bc_server/common.py
mcp_bc_server/resources.py
mcp_bc_server/server.py
mcp_bc_server/tools.py
mcp_business_central_server-0.1.2.dist-info/licenses/LICENSE
mcp_business_central_server-0.1.2.dist-info/METADATA
mcp_business_central_server-0.1.2.dist-info/WHEEL
mcp_business_central_server-0.1.2.dist-info/entry_points.txt
mcp_business_central_server-0.1.2.dist-info/top_level.txt
mcp_business_central_server-0.1.2.dist-info/RECORD
