Metadata-Version: 2.4
Name: mcp-business-central-server
Version: 0.1.2
Summary: MCP Server for Microsoft Dynamics 365 Business Central
Author: sofias tech
License-Expression: MIT
Project-URL: Homepage, https://github.com/Sofias-ai/mcp-business-central-server
Classifier: Programming Language :: Python :: 3
Classifier: Programming Language :: Python :: 3.10
Requires-Python: >=3.10
License-File: LICENSE
Requires-Dist: mcp>=1.2.1
Requires-Dist: requests>=2.28.0
Requires-Dist: python-dotenv>=1.0.0
Dynamic: license-file
